fuzzy_parser/__init__.py
fuzzy_parser/__main__.py
fuzzy_parser/engine.py
fuzzy_parser-0.2.59.dist-info/LICENSE
fuzzy_parser-0.2.59.dist-info/METADATA
fuzzy_parser-0.2.59.dist-info/WHEEL
fuzzy_parser-0.2.59.dist-info/entry_points.txt
fuzzy_parser-0.2.59.dist-info/top_level.txt
fuzzy_parser-0.2.59.dist-info/RECORD
