Metadata-Version: 2.1
Name: fuzzy-parser
Version: 0.2.59
Summary: A parser for fuzzy dates
Home-page: https://github.com/crgz/fuzzy_dates
Author: Real Python
Author-email: conrado.rgz@gmail.com
License: MIT
Classifier: License :: OSI Approved :: MIT License
Classifier: Programming Language :: Python :: 3
Classifier: Programming Language :: Python :: 3.7
License-File: LICENSE
Requires-Dist: pytest
Requires-Dist: pyswip
